README.md
setup.py
FLF/__init__.py
FLF/connectors.py
FLF/exceptions.py
FLF/procedure.py
FLF/store.py
FLF/streams.py
FLF/version.py
FLF.egg-info/PKG-INFO
FLF.egg-info/SOURCES.txt
FLF.egg-info/dependency_links.txt
FLF.egg-info/requires.txt
FLF.egg-info/top_level.txt